marktplaats/__init__.py
marktplaats/api_types.py
marktplaats/categories.py
marktplaats/config.py
marktplaats/l1_categories.json
marktplaats/l2_categories.json
marktplaats/models/__init__.py
marktplaats/models/listing.py
marktplaats/models/listing_image.py
marktplaats/models/listing_location.py
marktplaats/models/listing_seller.py
marktplaats/models/price_type.py
marktplaats/py.typed
marktplaats/query.py
marktplaats/utils.py
marktplaats-0.4.0.dist-info/WHEEL
marktplaats-0.4.0.dist-info/METADATA
marktplaats-0.4.0.dist-info/RECORD
