Metadata-Version: 2.4
Name: marktplaats
Version: 0.4.0
Summary: A small Python package to request listings from marktplaats.nl
Author: Jens de Ruiter
Author-email: Jens de Ruiter <me@jensderuiter.dev>
License-Expression: MIT
Classifier: License :: OSI Approved :: MIT License
Classifier: Operating System :: OS Independent
Classifier: Programming Language :: Python :: 3 :: Only
Classifier: Programming Language :: Python :: 3.9
Classifier: Programming Language :: Python :: 3.10
Classifier: Programming Language :: Python :: 3.11
Classifier: Programming Language :: Python :: 3.12
Classifier: Programming Language :: Python :: 3.13
Requires-Dist: beautifulsoup4>=4.13.4
Requires-Dist: requests>=2.28.2
Requires-Dist: typing-extensions>=4.13.2
Requires-Python: >=3.9
Project-URL: bugs, https://github.com/jensjeflensje/marktplaats-py/issues
Project-URL: homepage, https://github.com/jensjeflensje/marktplaats-py
